fast_resume/__init__.py
fast_resume/cli.py
fast_resume/config.py
fast_resume/index.py
fast_resume/logging_config.py
fast_resume/query.py
fast_resume/search.py
fast_resume/adapters/__init__.py
fast_resume/adapters/base.py
fast_resume/adapters/claude.py
fast_resume/adapters/codex.py
fast_resume/adapters/copilot.py
fast_resume/adapters/copilot_vscode.py
fast_resume/adapters/crush.py
fast_resume/adapters/opencode.py
fast_resume/adapters/vibe.py
fast_resume/assets/claude.png
fast_resume/assets/codex.png
fast_resume/assets/copilot-cli.png
fast_resume/assets/copilot-vscode.png
fast_resume/assets/crush.png
fast_resume/assets/opencode.png
fast_resume/assets/vibe.png
fast_resume/tui/__init__.py
fast_resume/tui/app.py
fast_resume/tui/filter_bar.py
fast_resume/tui/modal.py
fast_resume/tui/preview.py
fast_resume/tui/query.py
fast_resume/tui/results_table.py
fast_resume/tui/search_input.py
fast_resume/tui/styles.py
fast_resume/tui/utils.py
fast_resume-1.14.1.dist-info/METADATA
fast_resume-1.14.1.dist-info/WHEEL
fast_resume-1.14.1.dist-info/entry_points.txt
fast_resume-1.14.1.dist-info/licenses/LICENSE
fast_resume-1.14.1.dist-info/RECORD
