Metadata-Version: 2.4
Name: fast-resume
Version: 1.14.1
Summary: Fuzzy finder for coding agent session history
License-File: LICENSE
Requires-Python: >=3.14
Requires-Dist: click>=8.0.0
Requires-Dist: humanize>=4.14.0
Requires-Dist: orjson>=3.10.0
Requires-Dist: rich>=13.0.0
Requires-Dist: tantivy>=0.25.0
Requires-Dist: textual-image>=0.8.4
Requires-Dist: textual>=0.47.0
